rle/__init__.py
tests/__init__.py
tests/test_decode.py
tests/test_encode.py
tests/test_mp_encode.py
python_rle-0.0.3.dist-info/LICENSE.txt
python_rle-0.0.3.dist-info/METADATA
python_rle-0.0.3.dist-info/WHEEL
python_rle-0.0.3.dist-info/top_level.txt
python_rle-0.0.3.dist-info/RECORD
