Metadata-Version: 2.1
Name: python-rle
Version: 0.0.3
Summary: Run-length encoding for data analysis in Python
Home-page: https://github.com/tnwei/pyrle
Author: Tan Nian Wei
Author-email: tannianwei@aggienetwork.com
License: UNKNOWN
Platform: UNKNOWN
Classifier: Programming Language :: Python :: 3
Classifier: License :: OSI Approved :: MIT License
Classifier: Operating System :: OS Independent
Requires-Python: >=3.5
